camphr_cli/.gitignore
camphr_cli/VERSION.py
camphr_cli/__init__.py
camphr_cli/__main__.py
camphr_cli/conf/train/config.yaml
camphr_cli/conf/train/example/ner.yaml
camphr_cli/config.py
camphr_cli/train.py
camphr_cli/utils.py
camphr_cli-0.1.0.dist-info/entry_points.txt
camphr_cli-0.1.0.dist-info/WHEEL
camphr_cli-0.1.0.dist-info/METADATA
camphr_cli-0.1.0.dist-info/RECORD
