Metadata-Version: 2.1
Name: camphr-cli
Version: 0.1.0
Summary: 
License: Apache-2.0
Author: Yohei Tamura
Author-email: tamuhey@gmail.com
Requires-Python: >=3.7,<4.0
Classifier: License :: OSI Approved :: Apache Software License
Classifier: Programming Language :: Python :: 3
Classifier: Programming Language :: Python :: 3.7
Classifier: Programming Language :: Python :: 3.8
Classifier: Programming Language :: Python :: 3.9
Requires-Dist: camphr_pipelines (>=0.1.0,<0.2.0)
Requires-Dist: fire (>=0.4.0,<0.5.0)
Requires-Dist: hydra-core (==0.11.3)
Requires-Dist: scikit-learn (>=0.22,<0.25)
